bits/__init__.py
bits/datetime/__init__.py
bits_datetime-1.20.1.dist-info/METADATA
bits_datetime-1.20.1.dist-info/WHEEL
bits_datetime-1.20.1.dist-info/top_level.txt
bits_datetime-1.20.1.dist-info/RECORD
