Metadata-Version: 2.1
Name: bits-datetime
Version: 1.20.1
Summary: BITS DateTime
Home-page: UNKNOWN
Author: Kathryn Amaral
Author-email: kamaral@broadinstitute.org
License: Apache Software License
Platform: UNKNOWN
Requires-Dist: pytz
Requires-Dist: python-dateutil
